netbox_maintenance_device/__init__.py
netbox_maintenance_device/admin.py
netbox_maintenance_device/database_healer.py
netbox_maintenance_device/forms.py
netbox_maintenance_device/models.py
netbox_maintenance_device/navigation.py
netbox_maintenance_device/tables.py
netbox_maintenance_device/template_content.py
netbox_maintenance_device/urls.py
netbox_maintenance_device/views.py
netbox_maintenance_device/api/__init__.py
netbox_maintenance_device/api/permissions.py
netbox_maintenance_device/api/serializers.py
netbox_maintenance_device/api/urls.py
netbox_maintenance_device/api/views.py
netbox_maintenance_device/locale/pt_BR/LC_MESSAGES/django.mo
netbox_maintenance_device/locale/pt_BR/LC_MESSAGES/django.po
netbox_maintenance_device/migrations/0001_initial.py
netbox_maintenance_device/migrations/0002_cleanup_notifications.py
netbox_maintenance_device/migrations/__init__.py
netbox_maintenance_device/static/netbox_maintenance_device/css/maintenance.css
netbox_maintenance_device/templates/netbox_maintenance_device/device_maintenance_buttons.html
netbox_maintenance_device/templates/netbox_maintenance_device/device_maintenance_section.html
netbox_maintenance_device/templates/netbox_maintenance_device/device_maintenance_tab.html
netbox_maintenance_device/templates/netbox_maintenance_device/maintenanceexecution.html
netbox_maintenance_device/templates/netbox_maintenance_device/maintenanceplan.html
netbox_maintenance_device/templates/netbox_maintenance_device/upcoming_maintenance.html
netbox_maintenance_device/templatetags/__init__.py
netbox_maintenance_device/templatetags/maintenance_extras.py
netbox_maintenance_device-1.2.3.dist-info/licenses/LICENSE
netbox_maintenance_device-1.2.3.dist-info/METADATA
netbox_maintenance_device-1.2.3.dist-info/WHEEL
netbox_maintenance_device-1.2.3.dist-info/top_level.txt
netbox_maintenance_device-1.2.3.dist-info/RECORD
