Metadata-Version: 2.4
Name: netbox-maintenance-device
Version: 1.2.3
Summary: NetBox plugin for device maintenance management with comprehensive REST API and Portuguese-BR support
Author-email: Diego Godoy <diegoalex-gdy@outlook.com>
Maintainer-email: Diego Godoy <diegoalex-gdy@outlook.com>
License: Apache-2.0
Project-URL: Homepage, https://github.com/diegogodoy06/netbox-maintenance-device
Project-URL: Bug Reports, https://github.com/diegogodoy06/netbox-maintenance-device/issues
Project-URL: Source, https://github.com/diegogodoy06/netbox-maintenance-device
Project-URL: Documentation, https://github.com/diegogodoy06/netbox-maintenance-device/blob/main/README.md
Project-URL: Changelog, https://github.com/diegogodoy06/netbox-maintenance-device/releases
Keywords: netbox,plugin,maintenance,device,preventive,corrective,api,rest,automation,infrastructure,django
Classifier: Development Status :: 5 - Production/Stable
Classifier: Intended Audience :: System Administrators
Classifier: Intended Audience :: Telecommunications Industry
Classifier: Operating System :: OS Independent
Classifier: Programming Language :: Python :: 3
Classifier: Programming Language :: Python :: 3.12
Classifier: Programming Language :: Python :: 3.13
Classifier: Programming Language :: Python :: 3.14
Classifier: Framework :: Django
Classifier: Topic :: System :: Networking
Classifier: Topic :: System :: Systems Administration
Requires-Python: >=3.12
License-File: LICENSE
Provides-Extra: dev
Requires-Dist: black>=22.0.0; extra == "dev"
Requires-Dist: flake8>=4.0.0; extra == "dev"
Requires-Dist: pytest>=7.0.0; extra == "dev"
Requires-Dist: pytest-django>=4.5.0; extra == "dev"
Requires-Dist: pre-commit>=2.20.0; extra == "dev"
Dynamic: license-file
